setup.py
kegmeter/__init__.py
kegmeter/web/DB.py
kegmeter/web/Web.py
kegmeter/web/__init__.py
kegmeter/web/db/schema.sql
kegmeter/web/static/admin.css
kegmeter/web/static/admin.js
kegmeter/web/static/app.js
kegmeter/web/static/bg-introduction.gif
kegmeter/web/static/common.js
kegmeter/web/static/favicon.ico
kegmeter/web/static/jquery-1.8.2.min.js
kegmeter/web/static/logo.gif
kegmeter/web/static/mobile.css
kegmeter/web/static/mysterybeer.png
kegmeter/web/static/page_delete.png
kegmeter/web/static/pbu_40_black.png
kegmeter/web/static/style.css
kegmeter/web/templates/admin.html
kegmeter/web/templates/index.html
kegmeter_web.egg-info/PKG-INFO
kegmeter_web.egg-info/SOURCES.txt
kegmeter_web.egg-info/dependency_links.txt
kegmeter_web.egg-info/namespace_packages.txt
kegmeter_web.egg-info/requires.txt
kegmeter_web.egg-info/top_level.txt
scripts/kegmeter_web.py