Metadata-Version: 1.0
Name: kegmeter-web
Version: 0.99.5
Summary: Kegmeter web server
Home-page: https://github.com/Dennovin/kegmeter
Author: OmniTI Computer Consulting, Inc.
Author-email: hello@omniti.com
License: MIT
Platform: UNKNOWN
